LICENSE.txt
MANIFEST.in
README.rst
loading.py
setup.py
loading.egg-info/PKG-INFO
loading.egg-info/SOURCES.txt
loading.egg-info/dependency_links.txt
loading.egg-info/top_level.txt