Metadata-Version: 1.0
Name: loading
Version: 0.0.1
Summary: simple loading bar in python
Home-page: http://www.github.com/myusuf3/loading
Author: Mahdi Yusuf
Author-email: yusuf.mahdi@gmail.com
License: MIT License
Platform: UNKNOWN
